data_pypes-0.1.9.dist-info/DESCRIPTION.rst
data_pypes-0.1.9.dist-info/METADATA
data_pypes-0.1.9.dist-info/RECORD
data_pypes-0.1.9.dist-info/WHEEL
data_pypes-0.1.9.dist-info/metadata.json
data_pypes-0.1.9.dist-info/top_level.txt
pypes/__init__.py
pypes/_version.py
pypes/logsetup.py
pypes/pypes.py
