Metadata-Version: 2.0
Name: data-pypes
Version: 0.1.9
Summary: A micro framework for processing and logging.
Home-page: https://github.com/isnok/data-pypes
Author: Konstantin Martini
Author-email: k@tuxcode.org
License: UNKNOWN
Keywords: logging,number-crunching
Platform: Debian/GNU Linux
Classifier: Development Status :: 3 - Alpha
Classifier: Programming Language :: Python
Classifier: Programming Language :: Python :: 2.7
Classifier: Programming Language :: Python :: 3.4
Classifier: Programming Language :: Python :: 3.5
Classifier: Topic :: System :: Software Distribution
Classifier: Topic :: Utilities
Classifier: Intended Audience :: Developers
Classifier: Operating System :: POSIX
Classifier: Operating System :: Unix
